Metadata-Version: 1.0
Name: fandjango
Version: 4.2
Summary: Fandjango makes it stupidly easy to create Facebook applications with Django.
Home-page: http://github.com/jgorset/fandjango
Author: Johannes Gorset
Author-email: jgorset@gmail.com
License: UNKNOWN
Platform: UNKNOWN
Classifier: Development Status :: 5 - Production/Stable
Classifier: Intended Audience :: Developers
Classifier: Natural Language :: English
Classifier: License :: OSI Approved :: MIT License
Classifier: Programming Language :: Python
Classifier: Programming Language :: Python :: 2.6
Classifier: Programming Language :: Python :: 2.7
